example_haskell_wheel-1.3.0.dist-info/METADATA
example_haskell_wheel-1.3.0.dist-info/top_level.txt
example_haskell_wheel-1.3.0.dist-info/WHEEL
example_haskell_wheel-1.3.0.dist-info/RECORD
example_haskell_wheel-1.3.0.dist-info/LICENSE
example_haskell_wheel-1.3.0.dist-info/entry_points.txt
example_haskell_wheel/binding.def
example_haskell_wheel/binding.i
example_haskell_wheel/_binding.cpython-39-x86_64-linux-gnu.so
example_haskell_wheel/__main__.py
example_haskell_wheel/_binding.py
example_haskell_wheel/__init__.py
example_haskell_wheel/binding.pyi
example_haskell_wheel/binding.py
example_haskell_wheel.libs/libHSghc-bignum-1-127186ba.3-ghc9.4.8.so
example_haskell_wheel.libs/libHSbase-4-aa9b568d.17.2.1-ghc9.4.8.so
example_haskell_wheel.libs/libffi-c83313dd.so.8
example_haskell_wheel.libs/libHSrts-1-032c7f83.0.2-ghc9.4.8.so
example_haskell_wheel.libs/libgmp-afec2dd4.so.10.2.0
example_haskell_wheel.libs/libHSghc-prim-0-75ad3391.9.1-ghc9.4.8.so
